holidayrules/__init__.py
holidayrules/version.py
holidayrules-0.0.1.dist-info/LICENSE
holidayrules-0.0.1.dist-info/METADATA
holidayrules-0.0.1.dist-info/WHEEL
holidayrules-0.0.1.dist-info/top_level.txt
holidayrules-0.0.1.dist-info/RECORD
